confbuilder/__init__.py
confbuilder/main.py
spark_config_builder-0.2.dist-info/LICENSE
spark_config_builder-0.2.dist-info/METADATA
spark_config_builder-0.2.dist-info/WHEEL
spark_config_builder-0.2.dist-info/top_level.txt
spark_config_builder-0.2.dist-info/RECORD
